[{"id":"RwXUgBm1yqky_0","nid":"h1v1k1_a545","pid":"paragrafos-545","eid":"agfot-38_29","cid":"RwXUgBm1yqky","aa":"0","source":"b","start":38.19166838146969,"end":46.50833479382279,"data":{"nid":"h1v1k1_a545","cid":"RwXUgBm1yqky","aa":0,"aa2":1,"s":38.19166838146969,"e":46.50833479382279,"source":"b","startmark":{"r":2,"c":0},"endmark":{"r":2,"c":26},"pstart":{"row":20,"col":0},"pend":{"row":23,"col":0},"subtext":"ερωτήσεις απαντήσεις 1 2 3"},"images":{"src":"?"},"action":{"follow":"?"},"color":"rgba(86.8752625965474, 56.65976787126079, 132.4914400473093, 0.15)","resize":true,"drag":true,"content":"ερωτήσεις απαντήσεις 1 2 3"}]